compressdir/__init__.py
compressdir/compressdir.py
compressdir-0.1.3.dist-info/LICENSE
compressdir-0.1.3.dist-info/METADATA
compressdir-0.1.3.dist-info/WHEEL
compressdir-0.1.3.dist-info/top_level.txt
compressdir-0.1.3.dist-info/RECORD
