Metadata-Version: 2.1
Name: compressdir
Version: 0.1.3
Summary: File/directory compression
Home-page: https://github.com/WKHAllen/compressdir
Author: Will Allen
Author-email: wkhallen@gmail.com
License: MIT
Keywords: compression,decompression,files,directories
Platform: UNKNOWN
Classifier: Intended Audience :: Developers
Classifier: Topic :: System :: Archiving :: Compression
Classifier: License :: OSI Approved :: MIT License
Classifier: Programming Language :: Python
Classifier: Programming Language :: Python :: 3
Classifier: Programming Language :: Python :: 3.5
Classifier: Programming Language :: Python :: 3.6
Classifier: Programming Language :: Python :: 3.7
